{
  "summary": {
    "generatedon": "2026-01-28T08:51:42Z",
    "parser": "MultiReportParser (2x OpenCoverParser)",
    "assemblies": 1,
    "classes": 13,
    "files": 13,
    "coveredlines": 16,
    "uncoveredlines": 354,
    "coverablelines": 370,
    "totallines": 662,
    "linecoverage": 4.3,
    "coveredbranches": 0,
    "totalbranches": 0,
    "coveredmethods": 4,
    "totalmethods": 47,
    "methodcoverage": 8.5
 },
  "coverage": {
    "assemblies": [
      { "name": "Production", "classes": 13, "coverage": 4.3, "coveredlines": 16, "coverablelines": 370, "totallines": 662, "branchcoverage": null, "coveredbranches": 0, "totalbranches": 0, "methodcoverage": 8.5, "coveredmethods": 4, "totalmethods": 47, "classesinassembly": [
        { "name": "AutoMoveObstacle", "coverage": 0, "coveredlines": 0, "coverablelines": 8, "totallines": 28, "branchcoverage": null, "coveredbranches": 0, "totalbranches": 0, "methodcoverage": 0, "coveredmethods": 0, "totalmethods": 2 },
        { "name": "Calculator", "coverage": 100, "coveredlines": 16, "coverablelines": 16, "totallines": 29, "branchcoverage": null, "coveredbranches": 0, "totalbranches": 0, "methodcoverage": 100, "coveredmethods": 4, "totalmethods": 4 },
        { "name": "CharacterRotator", "coverage": 0, "coveredlines": 0, "coverablelines": 14, "totallines": 26, "branchcoverage": null, "coveredbranches": 0, "totalbranches": 0, "methodcoverage": 0, "coveredmethods": 0, "totalmethods": 3 },
        { "name": "ConcurrentDictionaryTest", "coverage": 0, "coveredlines": 0, "coverablelines": 66, "totallines": 96, "branchcoverage": null, "coveredbranches": 0, "totalbranches": 0, "methodcoverage": 0, "coveredmethods": 0, "totalmethods": 3 },
        { "name": "ConcurrentQueueTest", "coverage": 0, "coveredlines": 0, "coverablelines": 62, "totallines": 92, "branchcoverage": null, "coveredbranches": 0, "totalbranches": 0, "methodcoverage": 0, "coveredmethods": 0, "totalmethods": 3 },
        { "name": "ConcurrentStackTest", "coverage": 0, "coveredlines": 0, "coverablelines": 62, "totallines": 92, "branchcoverage": null, "coveredbranches": 0, "totalbranches": 0, "methodcoverage": 0, "coveredmethods": 0, "totalmethods": 3 },
        { "name": "DotProductDetector", "coverage": 0, "coveredlines": 0, "coverablelines": 36, "totallines": 87, "branchcoverage": null, "coveredbranches": 0, "totalbranches": 0, "methodcoverage": 0, "coveredmethods": 0, "totalmethods": 8 },
        { "name": "DungeonLoader", "coverage": 0, "coveredlines": 0, "coverablelines": 28, "totallines": 56, "branchcoverage": null, "coveredbranches": 0, "totalbranches": 0, "methodcoverage": 0, "coveredmethods": 0, "totalmethods": 5 },
        { "name": "LiftableObstacle", "coverage": 0, "coveredlines": 0, "coverablelines": 16, "totallines": 31, "branchcoverage": null, "coveredbranches": 0, "totalbranches": 0, "methodcoverage": 0, "coveredmethods": 0, "totalmethods": 3 },
        { "name": "MovableObstacle", "coverage": 0, "coveredlines": 0, "coverablelines": 34, "totallines": 55, "branchcoverage": null, "coveredbranches": 0, "totalbranches": 0, "methodcoverage": 0, "coveredmethods": 0, "totalmethods": 4 },
        { "name": "NavMeshObserver", "coverage": 0, "coveredlines": 0, "coverablelines": 7, "totallines": 20, "branchcoverage": null, "coveredbranches": 0, "totalbranches": 0, "methodcoverage": 0, "coveredmethods": 0, "totalmethods": 3 },
        { "name": "TargetMover", "coverage": 0, "coveredlines": 0, "coverablelines": 10, "totallines": 26, "branchcoverage": null, "coveredbranches": 0, "totalbranches": 0, "methodcoverage": 0, "coveredmethods": 0, "totalmethods": 3 },
        { "name": "UnitaskExample", "coverage": 0, "coveredlines": 0, "coverablelines": 11, "totallines": 24, "branchcoverage": null, "coveredbranches": 0, "totalbranches": 0, "methodcoverage": 0, "coveredmethods": 0, "totalmethods": 3 } ] } ]
  }
}